refire/__init__.py
refire/refire.py
refire-0.1.1.dist-info/WHEEL
refire-0.1.1.dist-info/METADATA
refire-0.1.1.dist-info/RECORD
