Metadata-Version: 2.3
Name: refire
Version: 0.1.1
Summary: A flexible Python decorator for retrying functions upon failure with support for exponential backoff, jitter, and configurable retry policies.
Keywords: retry,retries,decorator,backoff,exponential-backoff,jitter,resilience,fault-tolerance,error-handling,function-wrapper,reliability,utilities,developer-tools
Author: Max Scheijen
Author-email: Max Scheijen <maxscheijen@protonmail.com>
License: Apache-2.0
Classifier: Intended Audience :: Developers
Classifier: License :: OSI Approved :: Apache Software License
Classifier: Programming Language :: Python
Classifier: Programming Language :: Python :: 3
Classifier: Programming Language :: Python :: 3 :: Only
Classifier: Programming Language :: Python :: 3.10
Classifier: Programming Language :: Python :: 3.11
Classifier: Programming Language :: Python :: 3.12
Classifier: Programming Language :: Python :: 3.13
Classifier: Topic :: Software Development :: Libraries
Classifier: Topic :: Software Development :: Libraries :: Python Modules
Classifier: Topic :: Utilities
Classifier: Operating System :: OS Independent
Requires-Dist: interrogate>=1.7.0 ; extra == 'dev'
Requires-Dist: mypy>=1.17.1 ; extra == 'dev'
Requires-Dist: pre-commit>=4.3.0 ; extra == 'dev'
Requires-Dist: pytest>=8.4.2 ; extra == 'dev'
Requires-Dist: pytest-cov>=7.0.0 ; extra == 'dev'
Requires-Dist: ruff>=0.12.12 ; extra == 'dev'
Maintainer: Max Scheijen
Maintainer-email: Max Scheijen <maxscheijen@protonmail.com>
Requires-Python: >=3.10
Project-URL: Documentation, https://github.com/maxscheijen/refire
Project-URL: Homepage, https://github.com/maxscheijen/refire
Project-URL: Issues, https://github.com/maxscheijen/refire/issues
Project-URL: Repository, https://github.com/maxscheijen/refire.git
Provides-Extra: dev
